edaha/__init__.py
edaha-0.0.0.dist-info/METADATA
edaha-0.0.0.dist-info/WHEEL
edaha-0.0.0.dist-info/top_level.txt
edaha-0.0.0.dist-info/RECORD
