Metadata-Version: 2.1
Name: edaha
Version: 0.0.0
Summary: T.B.A.
Home-page: https://github.com/not-so-fat/edaha
Author: @not-so-fat
Author-email: conjurer.not.so.fat@gmail.com
License: UNKNOWN
Platform: UNKNOWN
Classifier: Programming Language :: Python :: 3
Classifier: License :: OSI Approved :: MIT License
Classifier: Operating System :: OS Independent
Requires-Python: >=3.9
Requires-Dist: ipywidgets
Requires-Dist: jupyterlab
Requires-Dist: jupyterlab-widgets
Requires-Dist: pandas
Requires-Dist: sidecar
